MANIFEST.in
README.md
setup.py
gar_cron/__init__.py
gar_cron/cfg.json
gar_cron/cron.py
gar_cron.egg-info/PKG-INFO
gar_cron.egg-info/SOURCES.txt
gar_cron.egg-info/dependency_links.txt
gar_cron.egg-info/entry_points.txt
gar_cron.egg-info/requires.txt
gar_cron.egg-info/top_level.txt