Metadata-Version: 2.1
Name: gar-cron
Version: 1.0.6
Summary: UNKNOWN
Home-page: https://github.com/prahladyeri/gar-cron
Author: Prahlad Yeri
Author-email: prahladyeri@yahoo.com
License: MIT
Platform: UNKNOWN
Classifier: Programming Language :: Python :: 3
Classifier: License :: OSI Approved :: MIT License
Classifier: Operating System :: OS Independent
